{
  "resource_state": 2,
  "athlete": {
    "id": 41933085,
    "resource_state": 1
  },
  "name": "\uc624\ud6c4 \ub2ec\ub9ac\uae30",
  "distance": 20300.0,
  "moving_time": 8650,
  "elapsed_time": 9827,
  "total_elevation_gain": 8.1,
  "type": "Run",
  "sport_type": "Run",
  "workout_type": 0,
  "id": 6090560464,
  "start_date": "2021-10-10T04:01:49Z",
  "start_date_local": "2021-10-10T13:01:49Z",
  "timezone": "(GMT+09:00) Asia/Seoul",
  "utc_offset": 32400.0,
  "location_city": null,
  "location_state": null,
  "location_country": null,
  "achievement_count": 0,
  "kudos_count": 2,
  "comment_count": 0,
  "athlete_count": 1,
  "photo_count": 0,
  "map": {
    "id": "a6090560464",
    "summary_polyline": "}n}cFgdxfWsA_OgASkBx@UpALv@nAtD~CdGXjDh@dAvA`A~CkAlAhCmAhAMbBrAvHpD`JfAx@rBXrBK~@s@XuDYoCsAyEaDqHuA}Ao@SgBp@sAs@u@j@h@qBdB_CK{AyBaEgAeAcAaCgEyDeCW}@Pi@n@Kf@RrA|AzD|BrDj@~At@dEd@z@jAVhCqAJf@`ChAoCnBYpA|ArH~D|JxElAlACp@e@Vw@JgDeB_IqCsHmAsB{@SaBj@kA_@SaBjAkBFw@eDmHoAmAo@qAwEqDiCBu@p@[pAF|@fGdLDbBx@vC~Bj@nBkAL~AfEQuDhBs@xB`ArE|AtF`CzErBtArE]j@kAPaCiCsLaE}HcBUiAb@iAu@Pi@s@HNs@rAgCmAoDaBmCGsAaCwB}EsCuCVIXb@bAHhCx@zChCvDhA`Hh@b@`BNdBuAbBfD_BdAAvCzAlGl@|@~AbFjAhAtAf@rDAt@wBL}Bc@gDkAwEgCuFuB_Ce@EoAl@w@m@_BBCoAlByAR{BuAcBkAgCc@wAaHkGwAWgBh@NvD~@fChBtCz@~Cn@v@SzATp@|BfAx@Ux@aAxADv@|Da@]aBbAMt@`@jBx@nGnDpHrArAzF?l@yBDeB[_DmAoEuBmFkBkCsAg@kAl@iAgAF{AMX`AcB@{@eC{DaBeEuCsByCmC}@AiAh@^\\]lF~BtC^`C~@pA@rAp@pCfCj@rBuA`An@F[bBrDg@g@JP}BJ[hAAhCxAvGn@p@lA~BOTn@dBhC`AtDD|@e@XaBI}DgAkFgCyGqBeC{@e@qADw@d@gAi@XiAMe@v@[^yBMu@_BaCk@aCuAu@oBmCcDuBNi@W?NXqBJy@pAYtATdBtCpErAnD?vBbAhBbCb@rBsA@^rAx@D|@mBp@QzAtA|IbBnE`BlC|@l@xF`@n@u@^eB@wBg@gCaA}AOwAwDaIEq@kCcAa@JGf@q@?mAmCJL]KrA_@d@cAeBuE_@}AaAg@qAyBoCoCwBmA_AQw@f@{@nBK~@ZK~ApDz@x@T`A`@`@t@nBKhB\\HGl@HUfAdCjBJxBuAbAZhJcIlGbMPfAf@d@aWE{BV`Ag@d@fCf@z@h@tDtAvEb@f@pA~BfAn@hDR~ASP_@I[XGHmAK{BRg@_@w@H{@gBmCqCoHs@}@uBy@yAl@Yc@c@p@QiCSS~AgAT_AkBeDe@sABe@w@qAsGcG",
    "resource_state": 2
  },
  "trainer": false,
  "commute": false,
  "manual": false,
  "private": false,
  "visibility": "followers_only",
  "flagged": false,
  "gear_id": null,
  "start_latlng": [
    37.511676,
    127.104841
  ],
  "end_latlng": [
    37.511884,
    127.107273
  ],
  "average_speed": 2.347,
  "max_speed": 8.4,
  "has_heartrate": true,
  "average_heartrate": 132.8,
  "max_heartrate": 144.0,
  "heartrate_opt_out": false,
  "display_hide_heartrate_option": true,
  "elev_high": 26.1,
  "elev_low": 15.2,
  "upload_id": 6472491774,
  "upload_id_str": "6472491774",
  "external_id": "341053FF-3B2C-42D9-9E3E-C0545718136D",
  "from_accepted_tag": false,
  "pr_count": 0,
  "total_photo_count": 0,
  "has_kudoed": false
}