{
  "resource_state": 2,
  "athlete": {
    "id": 41933085,
    "resource_state": 1
  },
  "name": "\uc624\ud6c4 \ub2ec\ub9ac\uae30",
  "distance": 14556.1,
  "moving_time": 8388,
  "elapsed_time": 8393,
  "total_elevation_gain": 37.8,
  "type": "Run",
  "sport_type": "Run",
  "workout_type": 0,
  "id": 4334578856,
  "start_date": "2020-11-14T06:19:19Z",
  "start_date_local": "2020-11-14T15:19:19Z",
  "timezone": "(GMT+09:00) Asia/Seoul",
  "utc_offset": 32400.0,
  "location_city": null,
  "location_state": null,
  "location_country": null,
  "achievement_count": 0,
  "kudos_count": 2,
  "comment_count": 0,
  "athlete_count": 1,
  "photo_count": 0,
  "map": {
    "id": "a4334578856",
    "summary_polyline": "ua|cF_k~fWi@?gBP{A?q@D_AAs@Fe@LqBFqDRK@OPq@`ASf@SSm@aAKIeEFsBLwA\\c@FaA\\y@d@cChAoB^wBdAwBv@wB~@_Bh@g@\\}Ad@ORiAfCw@lAWjAWt@o@v@g@TOn@XWPPDJAFI^cA|CMl@[`@mBtAaGt@{A^cAd@}@X]Ta@Po@n@o@`@sCxAIT_@BMNOh@M?LBDE@QIKc@I_CqA[?eAhAMREX{@|B]nAgCdHOj@QbACh@Dv@KfBK`A@L@CClCDvAZjC|@hGb@tBH~@Af@BTTh@nAtB@RGPBh@U`BUx@OxABv@ExCBfFCXBxDAdABrAAdCBx@Eb@BvACd@@z@Cp@FpDCpJ@|ILhBd@jANr@U`Ag@|@Wt@_@v@CLTX^RP\\pBlAx@r@v@xAf@xAp@vAPj@XbBV~@bAnC\\h@f@jATZbBbDp@vDj@`BVf@Lh@d@~@Ff@P|@rAtDj@nBb@tBRp@CTYH?LLb@h@vCx@vGFlAXnDXjFLfBLdAVnETlI?zFKvEDh@K\\@XCp@KhA@f@c@`Gk@rF?Ne@dEKbB}@dJEt@m@xFHR@LCI?BACGBG\\@p@^zB@b@Gv@@\\JdAXdAb@t@ZVUQ_@m@Sg@Sy@G]Cs@FeBE]_@}A?U@w@JeADiAx@oIJcAAQ@Bx@eJ|@_J\\gFBmA@J?CPuGD}DGyGK}DY{FWwCIwA?OJUm@}IAq@WgBa@eDq@{DFQAMNEBM_@yACAKq@_@yAX}@?GCEEFDEBPQHKEEIB@?D@C@DSUMEkA{CW_AOUIWM_AKc@MUw@{BSoAa@qBiAkB{@aBO_@g@y@c@iAQs@MOK@DDDCBIOc@UoAyA{DW_A[s@i@w@}@q@wBqAi@y@O]a@Kk@k@Wu@WaBQ]Y_@WQc@S_@Ka@E{@[{B{B}EiFwAcBaFeFYc@_@@_@c@e@]wAq@eBg@q@A}AW_F}AiAe@aAWwAm@kBmAcAy@IDEFDX?CABDG?GC?@C@HI]KQUQQ[gAmAkB_CiAcAc@u@k@e@o@_AmAwA{@e@{@[CEBKi@Aa@Oc@IIMy@s@uBuAq@k@gBoA[[kAu@GMBW@?IVEZGP?ZWh@FT@TBHCK\\wBXk@",
    "resource_state": 2
  },
  "trainer": false,
  "commute": false,
  "manual": false,
  "private": false,
  "visibility": "followers_only",
  "flagged": false,
  "gear_id": null,
  "start_latlng": [
    37.501814,
    127.137779
  ],
  "end_latlng": [
    37.540988,
    127.118377
  ],
  "average_speed": 1.735,
  "max_speed": 10.8,
  "has_heartrate": false,
  "heartrate_opt_out": false,
  "display_hide_heartrate_option": false,
  "elev_high": 30.2,
  "elev_low": 14.0,
  "upload_id": 4633518929,
  "upload_id_str": "4633518929",
  "external_id": "2ea8b7ce-eab4-4d9a-8cdf-86bfdc188508-activity.fit",
  "from_accepted_tag": false,
  "pr_count": 0,
  "total_photo_count": 0,
  "has_kudoed": false
}