{
  "resource_state": 2,
  "athlete": {
    "id": 41933085,
    "resource_state": 1
  },
  "name": "\uc800\ub141 \ub2ec\ub9ac\uae30",
  "distance": 10042.7,
  "moving_time": 4011,
  "elapsed_time": 4014,
  "total_elevation_gain": 18.3,
  "type": "Run",
  "sport_type": "Run",
  "workout_type": 0,
  "id": 3775243108,
  "start_date": "2020-07-17T11:36:51Z",
  "start_date_local": "2020-07-17T20:36:51Z",
  "timezone": "(GMT+09:00) Asia/Seoul",
  "utc_offset": 32400.0,
  "location_city": null,
  "location_state": null,
  "location_country": null,
  "achievement_count": 0,
  "kudos_count": 2,
  "comment_count": 0,
  "athlete_count": 1,
  "photo_count": 0,
  "map": {
    "id": "a3775243108",
    "summary_polyline": "o_|cFik~fWi@?cADi@P]BsBAO?MDoACk@Dm@LkAAwBTy@?}@TiAh@WH_A_@a@GcCPiCHa@FuCt@}At@o@d@y@^[Dc@@m@Ji@PuC~A_C|@k@NWPWHg@LQL]Lg@Vc@Lu@r@k@x@c@rAe@p@GZAd@Ol@a@fA]r@e@hBMZa@tASh@]h@}@p@k@ReATqAPWLwARMH}@Lg@Re@VOCIISk@GGM@e@\\e@PqB`Bm@Zq@LgAB}@Hm@\\YVMTk@n@IBe@@e@DIDUz@S^Ib@k@|AG\\a@`ASr@i@lAMl@e@pAGVAJ@p@I^BfAOpBGbE?l@LvALr@h@~Dd@`CNhAHjADpAV`@Xj@b@j@Rl@?HO\\ETCdAEf@WbBGz@?f@BXE~@DbDCpA?tABr@AdD@rA?xBE`@?f@DrDAtA@nBC|@BxB?vBC~@BnAAf@@bB?EO@AJN`CCt@H~AENIL?HD?DKB_@IcABeBAyABoAAcADy@G}A@o@DYEk@@cBCq@BoAAa@?kBCmADuBAQ@W@uCCeADy@EsABiAGcABwAI}BFiC@}Ad@uCB_@COLiA?c@C]EQq@eA]q@GSIwAI}@kAeIY{AIu@GyAHqER_CGcALcApBqGTm@Le@HQx@wBRy@Xs@HKFAR?n@CHCTSP[He@d@Wl@On@?zAK^Il@Wb@Y|@s@JO^Sb@K`@SJBNl@PBpAi@n@MzBOnBUd@ObAe@f@a@v@wAd@_Bz@}Bh@}BXo@NcAN]Z_@Re@ZcAJULMl@i@ZKt@_@dA]z@a@`Bm@l@YHIhCcAICj@ShA[n@Uf@Gn@U^Sd@Qb@YjAi@bBYx@Sj@An@IhAAt@KV?XCz@Cl@WYNj@EbBG`@IX?\\BZGZ@\\Ez@A|AS`@Kz@DJAl@?pAB^CfAMp@@x@I\\@vAE",
    "resource_state": 2
  },
  "trainer": false,
  "commute": false,
  "manual": false,
  "private": false,
  "visibility": "followers_only",
  "flagged": false,
  "gear_id": null,
  "start_latlng": [
    37.501544,
    127.137078
  ],
  "end_latlng": [
    37.500985,
    127.138431
  ],
  "average_speed": 2.504,
  "max_speed": 9.8,
  "has_heartrate": false,
  "heartrate_opt_out": false,
  "display_hide_heartrate_option": false,
  "elev_high": 29.0,
  "elev_low": 18.9,
  "upload_id": 4034266829,
  "upload_id_str": "4034266829",
  "external_id": "01d4e348-6627-4a0b-b287-9beb5e053fde-activity.fit",
  "from_accepted_tag": false,
  "pr_count": 0,
  "total_photo_count": 0,
  "has_kudoed": false
}