{
  "resource_state": 2,
  "athlete": {
    "id": 41933085,
    "resource_state": 1
  },
  "name": "Afternoon Run",
  "distance": 6444.7,
  "moving_time": 2530,
  "elapsed_time": 2776,
  "total_elevation_gain": 145.9,
  "type": "Run",
  "sport_type": "Run",
  "workout_type": null,
  "id": 12543163906,
  "start_date": "2024-09-28T06:07:36Z",
  "start_date_local": "2024-09-28T15:07:36Z",
  "timezone": "(GMT+09:00) Asia/Seoul",
  "utc_offset": 32400.0,
  "location_city": null,
  "location_state": null,
  "location_country": null,
  "achievement_count": 0,
  "kudos_count": 0,
  "comment_count": 0,
  "athlete_count": 1,
  "photo_count": 0,
  "map": {
    "id": "a12543163906",
    "summary_polyline": "slhdFkgofWCEVBx@E?QFWLYD]EaAHy@Ea@EMOOMA_@AWF_@ZMDU\\GX[h@CVFXL^Xh@@n@C|@BFF@FEBUNYF]FQR@BCFIFWDi@C{@@u@Ea@Me@a@[M@EDENIJ]FIDEFGRIL[XCH?PDTRv@JXFf@Lh@@PEVB?h@a@NGXc@n@KLGHKDM?ME_@WeA?[UkA[SSCIDWROV[d@m@n@EHJr@Rl@Fb@Nb@@PCZT?hAq@JKFK@QBIVWLSDw@CQEkAG_@KO]Oa@Bg@Ls@`A_@TEH?VBXPd@T^Pf@Fv@DLDBF?d@WPa@Jc@LQb@_@B]GsAE[@_@CIEEk@SM@CBAFOBg@QG@Uz@@RE^CFQTCJANBNb@v@Fx@Jh@?PPFLALENMHsADETEJ?BCXo@FY@YE]Cu@G_@KKa@YKAK@a@Lc@`@CRD`@EJOJUHKLAVDZLh@PZH\\Bn@DNHBJAVURDROZg@Bg@FOJGRA@GEu@?a@U{AEOSSKOOAWR_@@WRIVIf@KJIREX@h@BRLXRx@Bz@JHLBRCHKN[\\cA\\q@JGFOB]AmAGYGMm@[KCo@NUZGr@GT[p@AZFj@^|ADVLFR?FCHMN_@XSLi@NUJIHQBkACg@E[KWKIc@OKIa@AINYX]v@OVEr@@LPn@Px@B|@HHR@PENQRi@XUL_@XUHUBq@A]YwAEGUQc@I{@l@CFCp@Wh@GTIJAJBPLXFh@Nj@B^BHDDTHN?DEFOR}@Ra@FGd@{@AkABUEi@MWi@_@OBGJOFOP[|@]b@O\\CRAJBHNXNl@HhANLPANKTy@\\e@Z]L[FeAGiAI_@]_@?WBKFKRMJCLK?IOo@@UBULWh@{@DEFAb@VPPf@VZ\\\\T`@^VRTTDNBl@FJJBd@@LDHFJPNZ|@hAb@x@f@t@\\^`@v@PTPj@BXAHIR]^a@n@s@bAS\\QN[`@MHKAYWw@kAWW]m@IGG?QDa@^_@T]t@YVU^Od@GHG@OCcAW]Uc@MAG@OQDiAbAQDSALGJDH?f@g@DAHITc@@CI_@C]AKGE",
    "resource_state": 2
  },
  "trainer": false,
  "commute": false,
  "manual": false,
  "private": false,
  "visibility": "followers_only",
  "flagged": false,
  "gear_id": null,
  "start_latlng": [
    37.567628,
    127.05926466
  ],
  "end_latlng": [
    37.56776767,
    127.05807129
  ],
  "average_speed": 2.547,
  "max_speed": 7.553,
  "average_cadence": 80.8,
  "has_heartrate": true,
  "average_heartrate": 157.9,
  "max_heartrate": 173.0,
  "heartrate_opt_out": false,
  "display_hide_heartrate_option": true,
  "elev_high": 37.4,
  "elev_low": 17.7,
  "upload_id": 13373427826,
  "upload_id_str": "13373427826",
  "external_id": "3300300748-1727503656-Run.tcx",
  "from_accepted_tag": false,
  "pr_count": 0,
  "total_photo_count": 0,
  "has_kudoed": false
}